{"name":"设计","slug":"设计","count":1,"postlist":[{"title":"搞设计必备的工具/资源/网站","uid":"7b9ffc72b5a7cb190c30b47bbc422642","slug":"design_tools","date":"2020-11-06T16:00:00.000Z","updated":"2021-03-25T05:29:23.000Z","comments":true,"path":"api/articles/design_tools.json","keywords":null,"cover":"/img/design_tools/index_banner.png","text":"给看官们推荐一下笔者常用的设计资源和网站 Dribbble—灵感之源 Dribbble 是全球最大的在线设计交流网站，来自世界各地的顶尖设计师经常在该站上发布自己的作品。 笔者平时会经常上去观摩大师的设计，获取配色灵感，提高审美标准，同时get到设计界的最新潮流。 笔者坚信，多欣...","link":"","photos":[],"count_time":{"symbolsCount":"1.9k","symbolsTime":"2 mins."},"categories":[{"name":"设计","slug":"设计","count":1,"path":"api/categories/设计.json"}],"tags":[{"name":"工具","slug":"工具","count":4,"path":"api/tags/工具.json"},{"name":"设计","slug":"设计","count":1,"path":"api/tags/设计.json"},{"name":"PPT","slug":"PPT","count":1,"path":"api/tags/PPT.json"}],"author":{"name":"菲尔普斯","slug":"blog-author","avatar":"https://avatars.githubusercontent.com/u/72149771?v=4","link":"/","description":"你曾经灼热的眼眶，是人生中少数的笨拙又可贵的时刻","socials":{"github":"","twitter":"","stackoverflow":"","wechat":"","qq":"","weibo":"","zhihu":"","csdn":"","juejin":"","customs":{}}}}]}